topsis/102217055.py
topsis/__init__.py
Topsis_Angad_Singh_Marwaha_102217055-0.1.0.dist-info/LICENSE
Topsis_Angad_Singh_Marwaha_102217055-0.1.0.dist-info/METADATA
Topsis_Angad_Singh_Marwaha_102217055-0.1.0.dist-info/WHEEL
Topsis_Angad_Singh_Marwaha_102217055-0.1.0.dist-info/top_level.txt
Topsis_Angad_Singh_Marwaha_102217055-0.1.0.dist-info/RECORD
